autodigipick/__init__.py
autodigipick/__main__.py
autodigipick-1.1.1.dist-info/LICENSE.txt
autodigipick-1.1.1.dist-info/METADATA
autodigipick-1.1.1.dist-info/WHEEL
autodigipick-1.1.1.dist-info/entry_points.txt
autodigipick-1.1.1.dist-info/top_level.txt
autodigipick-1.1.1.dist-info/RECORD
