Metadata-Version: 2.1
Name: autodigipick
Version: 1.1.1
Summary: Automatically solve Starfield Digipick puzzles with the press of a button.
Author-email: ReggX <dev@reggx.eu>
License: MIT License
Project-URL: Homepage, https://github.com/reggx/autodigipick
Keywords: Starfield,solver,OpenCV
Classifier: Development Status :: 4 - Beta
Classifier: Intended Audience :: End Users/Desktop
Classifier: Topic :: Games/Entertainment
Classifier: License :: OSI Approved :: MIT License
Classifier: Programming Language :: Python :: 3
Classifier: Programming Language :: Python :: 3.8
Classifier: Programming Language :: Python :: 3.9
Classifier: Programming Language :: Python :: 3.10
Classifier: Programming Language :: Python :: 3.11
Classifier: Programming Language :: Python :: 3 :: Only
Requires-Python: >=3.8
License-File: LICENSE.txt
Requires-Dist: opencv-python
Requires-Dist: keyboard
Requires-Dist: mss
Requires-Dist: numpy
Requires-Dist: pydirectinput-rgx
Requires-Dist: pytesseract
